CHANGES.txt
MANIFEST.in
README.rst
bootstrap.py
buildout.cfg
setup.py
tox.ini
python_gettext.egg-info/PKG-INFO
python_gettext.egg-info/SOURCES.txt
python_gettext.egg-info/dependency_links.txt
python_gettext.egg-info/not-zip-safe
python_gettext.egg-info/requires.txt
python_gettext.egg-info/top_level.txt
pythongettext/__init__.py
pythongettext/msgfmt.py
pythongettext/tests/__init__.py
pythongettext/tests/test.mo
pythongettext/tests/test.po
pythongettext/tests/test.pot
pythongettext/tests/test2.mo
pythongettext/tests/test2.po
pythongettext/tests/test3.mo
pythongettext/tests/test3.po
pythongettext/tests/test4.po
pythongettext/tests/test5.po
pythongettext/tests/test6.mo
pythongettext/tests/test6.po
pythongettext/tests/test_compile.py
pythongettext/tests/test_empty.mo
pythongettext/tests/test_empty.po
pythongettext/tests/test_escape.po
pythongettext/tests/test_unicode_bom.mo
pythongettext/tests/test_unicode_bom.po