Metadata-Version: 1.0
Name: python-gettext
Version: 2.0
Summary: Python Gettext po to mo file compiler.
Home-page: http://pypi.python.org/pypi/python-gettext
Author: Hanno Schlichting
Author-email: hanno@hannosch.eu
License: BSD
Keywords: Python Gettext Msgctxt
Platform: UNKNOWN
Classifier: Development Status :: 5 - Production/Stable
Classifier: Intended Audience :: Developers
Classifier: License :: OSI Approved :: BSD License
Classifier: Operating System :: OS Independent
Classifier: Programming Language :: Python
Classifier: Programming Language :: Python :: 2.6
Classifier: Programming Language :: Python :: 2.7
Classifier: Programming Language :: Python :: 3
Classifier: Programming Language :: Python :: 3.2
Classifier: Programming Language :: Python :: Implementation :: CPython
Classifier: Programming Language :: Python :: Implementation :: PyPy
Classifier: Topic :: Software Development :: Internationalization
Classifier: Topic :: Software Development :: Localization
